{
  "id": "6af1056a-ba5e-47bf-a12f-5c80635a371c",
  "prevId": "00000000-0000-0000-0000-000000000000",
  "version": "7",
  "dialect": "postgresql",
  "tables": {
    "public.genre": {
      "name": "genre",
      "schema": "",
      "columns": {
        "id": {
          "name": "id",
          "type": "uuid",
          "primaryKey": true,
          "notNull": true,
          "default": "gen_random_uuid()"
        },
        "name": {
          "name": "name",
          "type": "varchar(255)",
          "primaryKey": false,
          "notNull": true
        }
      },
      "indexes": {},
      "foreignKeys": {},
      "compositePrimaryKeys": {},
      "uniqueConstraints": {}
    },
    "public.guest": {
      "name": "guest",
      "schema": "",
      "columns": {
        "id": {
          "name": "id",
          "type": "uuid",
          "primaryKey": true,
          "notNull": true,
          "default": "gen_random_uuid()"
        },
        "session_id": {
          "name": "session_id",
          "type": "uuid",
          "primaryKey": false,
          "notNull": false
        },
        "feedback": {
          "name": "feedback",
          "type": "text",
          "primaryKey": false,
          "notNull": true
        },
        "tip": {
          "name": "tip",
          "type": "integer",
          "primaryKey": false,
          "notNull": false,
          "default": 0
        },
        "created_at": {
          "name": "created_at",
          "type": "timestamp",
          "primaryKey": false,
          "notNull": false,
          "default": "now()"
        }
      },
      "indexes": {},
      "foreignKeys": {
        "guest_session_id_session_id_fk": {
          "name": "guest_session_id_session_id_fk",
          "tableFrom": "guest",
          "tableTo": "session",
          "columnsFrom": [
            "session_id"
          ],
          "columnsTo": [
            "id"
          ],
          "onDelete": "cascade",
          "onUpdate": "no action"
        }
      },
      "compositePrimaryKeys": {},
      "uniqueConstraints": {}
    },
    "public.lip": {
      "name": "lip",
      "schema": "",
      "columns": {
        "id": {
          "name": "id",
          "type": "uuid",
          "primaryKey": true,
          "notNull": true,
          "default": "gen_random_uuid()"
        },
        "session_id": {
          "name": "session_id",
          "type": "uuid",
          "primaryKey": false,
          "notNull": true
        },
        "song_id": {
          "name": "song_id",
          "type": "uuid",
          "primaryKey": false,
          "notNull": true
        },
        "guest_id": {
          "name": "guest_id",
          "type": "uuid",
          "primaryKey": false,
          "notNull": true
        },
        "singer_name": {
          "name": "singer_name",
          "type": "varchar(255)",
          "primaryKey": false,
          "notNull": true
        },
        "status": {
          "name": "status",
          "type": "text",
          "primaryKey": false,
          "notNull": true,
          "default": "'idle'"
        },
        "sort_number": {
          "name": "sort_number",
          "type": "integer",
          "primaryKey": false,
          "notNull": false
        },
        "created_at": {
          "name": "created_at",
          "type": "timestamp",
          "primaryKey": false,
          "notNull": false,
          "default": "now()"
        },
        "updated_at": {
          "name": "updated_at",
          "type": "timestamp",
          "primaryKey": false,
          "notNull": false,
          "default": "now()"
        }
      },
      "indexes": {},
      "foreignKeys": {
        "lip_session_id_session_id_fk": {
          "name": "lip_session_id_session_id_fk",
          "tableFrom": "lip",
          "tableTo": "session",
          "columnsFrom": [
            "session_id"
          ],
          "columnsTo": [
            "id"
          ],
          "onDelete": "cascade",
          "onUpdate": "no action"
        },
        "lip_song_id_song_id_fk": {
          "name": "lip_song_id_song_id_fk",
          "tableFrom": "lip",
          "tableTo": "song",
          "columnsFrom": [
            "song_id"
          ],
          "columnsTo": [
            "id"
          ],
          "onDelete": "cascade",
          "onUpdate": "no action"
        },
        "lip_guest_id_guest_id_fk": {
          "name": "lip_guest_id_guest_id_fk",
          "tableFrom": "lip",
          "tableTo": "guest",
          "columnsFrom": [
            "guest_id"
          ],
          "columnsTo": [
            "id"
          ],
          "onDelete": "cascade",
          "onUpdate": "no action"
        }
      },
      "compositePrimaryKeys": {},
      "uniqueConstraints": {}
    },
    "public.session": {
      "name": "session",
      "schema": "",
      "columns": {
        "id": {
          "name": "id",
          "type": "uuid",
          "primaryKey": true,
          "notNull": true,
          "default": "gen_random_uuid()"
        },
        "title": {
          "name": "title",
          "type": "varchar(255)",
          "primaryKey": false,
          "notNull": true
        },
        "setlist_id": {
          "name": "setlist_id",
          "type": "uuid",
          "primaryKey": false,
          "notNull": true
        },
        "is_demo": {
          "name": "is_demo",
          "type": "boolean",
          "primaryKey": false,
          "notNull": false,
          "default": false
        },
        "is_locked": {
          "name": "is_locked",
          "type": "boolean",
          "primaryKey": false,
          "notNull": false,
          "default": false
        },
        "has_tip_collection": {
          "name": "has_tip_collection",
          "type": "boolean",
          "primaryKey": false,
          "notNull": false,
          "default": false
        },
        "starts_at": {
          "name": "starts_at",
          "type": "timestamp",
          "primaryKey": false,
          "notNull": false
        },
        "ends_at": {
          "name": "ends_at",
          "type": "timestamp",
          "primaryKey": false,
          "notNull": false
        },
        "created_at": {
          "name": "created_at",
          "type": "timestamp",
          "primaryKey": false,
          "notNull": false,
          "default": "now()"
        }
      },
      "indexes": {},
      "foreignKeys": {},
      "compositePrimaryKeys": {},
      "uniqueConstraints": {}
    },
    "public.setlist": {
      "name": "setlist",
      "schema": "",
      "columns": {
        "id": {
          "name": "id",
          "type": "uuid",
          "primaryKey": true,
          "notNull": true,
          "default": "gen_random_uuid()"
        },
        "title": {
          "name": "title",
          "type": "varchar(255)",
          "primaryKey": false,
          "notNull": true
        },
        "created_at": {
          "name": "created_at",
          "type": "timestamp",
          "primaryKey": false,
          "notNull": false,
          "default": "now()"
        },
        "updated_at": {
          "name": "updated_at",
          "type": "timestamp",
          "primaryKey": false,
          "notNull": false,
          "default": "now()"
        }
      },
      "indexes": {},
      "foreignKeys": {},
      "compositePrimaryKeys": {},
      "uniqueConstraints": {}
    },
    "public.setlist_to_song": {
      "name": "setlist_to_song",
      "schema": "",
      "columns": {
        "setlist_id": {
          "name": "setlist_id",
          "type": "uuid",
          "primaryKey": false,
          "notNull": true
        },
        "song_id": {
          "name": "song_id",
          "type": "uuid",
          "primaryKey": false,
          "notNull": true
        }
      },
      "indexes": {},
      "foreignKeys": {
        "setlist_to_song_setlist_id_setlist_id_fk": {
          "name": "setlist_to_song_setlist_id_setlist_id_fk",
          "tableFrom": "setlist_to_song",
          "tableTo": "setlist",
          "columnsFrom": [
            "setlist_id"
          ],
          "columnsTo": [
            "id"
          ],
          "onDelete": "cascade",
          "onUpdate": "no action"
        },
        "setlist_to_song_song_id_song_id_fk": {
          "name": "setlist_to_song_song_id_song_id_fk",
          "tableFrom": "setlist_to_song",
          "tableTo": "song",
          "columnsFrom": [
            "song_id"
          ],
          "columnsTo": [
            "id"
          ],
          "onDelete": "cascade",
          "onUpdate": "no action"
        }
      },
      "compositePrimaryKeys": {
        "setlist_to_song_setlist_id_song_id_pk": {
          "name": "setlist_to_song_setlist_id_song_id_pk",
          "columns": [
            "setlist_id",
            "song_id"
          ]
        }
      },
      "uniqueConstraints": {}
    },
    "public.song": {
      "name": "song",
      "schema": "",
      "columns": {
        "id": {
          "name": "id",
          "type": "uuid",
          "primaryKey": true,
          "notNull": true,
          "default": "gen_random_uuid()"
        },
        "artist": {
          "name": "artist",
          "type": "varchar(255)",
          "primaryKey": false,
          "notNull": true
        },
        "title": {
          "name": "title",
          "type": "varchar(255)",
          "primaryKey": false,
          "notNull": true
        },
        "lyrics": {
          "name": "lyrics",
          "type": "text",
          "primaryKey": false,
          "notNull": true
        },
        "is_favorite": {
          "name": "is_favorite",
          "type": "boolean",
          "primaryKey": false,
          "notNull": true,
          "default": false
        },
        "created_at": {
          "name": "created_at",
          "type": "timestamp",
          "primaryKey": false,
          "notNull": false,
          "default": "now()"
        },
        "updated_at": {
          "name": "updated_at",
          "type": "timestamp",
          "primaryKey": false,
          "notNull": false,
          "default": "now()"
        }
      },
      "indexes": {},
      "foreignKeys": {},
      "compositePrimaryKeys": {},
      "uniqueConstraints": {}
    },
    "public.song_to_genre": {
      "name": "song_to_genre",
      "schema": "",
      "columns": {
        "song_id": {
          "name": "song_id",
          "type": "uuid",
          "primaryKey": false,
          "notNull": true
        },
        "genre_id": {
          "name": "genre_id",
          "type": "uuid",
          "primaryKey": false,
          "notNull": true
        }
      },
      "indexes": {},
      "foreignKeys": {
        "song_to_genre_song_id_song_id_fk": {
          "name": "song_to_genre_song_id_song_id_fk",
          "tableFrom": "song_to_genre",
          "tableTo": "song",
          "columnsFrom": [
            "song_id"
          ],
          "columnsTo": [
            "id"
          ],
          "onDelete": "cascade",
          "onUpdate": "no action"
        },
        "song_to_genre_genre_id_genre_id_fk": {
          "name": "song_to_genre_genre_id_genre_id_fk",
          "tableFrom": "song_to_genre",
          "tableTo": "genre",
          "columnsFrom": [
            "genre_id"
          ],
          "columnsTo": [
            "id"
          ],
          "onDelete": "cascade",
          "onUpdate": "no action"
        }
      },
      "compositePrimaryKeys": {
        "song_to_genre_song_id_genre_id_pk": {
          "name": "song_to_genre_song_id_genre_id_pk",
          "columns": [
            "song_id",
            "genre_id"
          ]
        }
      },
      "uniqueConstraints": {}
    }
  },
  "enums": {},
  "schemas": {},
  "sequences": {},
  "_meta": {
    "columns": {},
    "schemas": {},
    "tables": {}
  }
}